aitpi/__init__.py
aitpi/command_registry.py
aitpi/constants.py
aitpi/consumer.py
aitpi/folder_watch.py
aitpi/input_converter.py
aitpi/input_initializer.py
aitpi/input_unit.py
aitpi/message.py
aitpi/mirrored_json.py
aitpi/pi_input_initializer.py
aitpi/printer.py
aitpi/pyqt6_key_map.py
aitpi/router.py
aitpi-1.0.1.dist-info/LICENSE
aitpi-1.0.1.dist-info/METADATA
aitpi-1.0.1.dist-info/WHEEL
aitpi-1.0.1.dist-info/top_level.txt
aitpi-1.0.1.dist-info/RECORD
