Metadata-Version: 2.1
Name: aitpi
Version: 1.0.1
Summary: A tool to setup arbitrary button configurations
Home-page: https://github.com/c3n3/aitpi
Author: Caden Churchman
Author-email: ccaden21@gmail.com
Project-URL: Bug Tracker, https://github.com/c3n3/aitpi/issues
Classifier: Programming Language :: Python :: 3
Classifier: License :: OSI Approved :: MIT License
Classifier: Operating System :: POSIX :: Linux
Requires-Python: >=3.6
License-File: LICENSE
